control.v
`timescale 1ns/1ps

module control (ir , pc_select, alu_instr, write_reg, input2_select, sw, lw, reg_write, link, immediate);
input wire[31:0] ir;
output reg[1:0] pc_select; // 0 = next line, 1 = branch, 2 = jr, 3 = j
output reg[3:0] alu_instr; // which operation alu will preform
output reg[4:0] write_reg; // register to write
output reg input2_select;  // 0 if input2 is in rt, 1 if immediate
output reg sw;             // 1 for sw
output reg lw;             // 1 for lw
output reg reg_write;      // 1 for writing to register
output reg link;           // 1 for jal
output reg[31:0] immediate;

wire[31:0] signed_im, unsigned_im;
assign signed_im = {{16{ir[15]}} , ir[15:0]};
assign unsigned_im = {16'd0 , ir[15:0]};

wire [4:0]rs,rt,rd;
assign rs = ir[25:21];
assign rt = ir[20:16];
assign rd = ir[15:11];

always@(ir) begin
    link = 0;
    sw = 0;
    lw = 0;
    immediate = signed_im;       

    if(ir[31:26] == 6'b000000) begin // R formats
        pc_select = 0;
        write_reg = rd;
        input2_select = 0;
        reg_write = 1;

        case(ir[5:0])
        6'b100000: alu_instr = 0; // add
        6'b100001: alu_instr = 0; // addu
        6'b100010: alu_instr = 1; // sub
        6'b100011: alu_instr = 1; // subu
        6'b100100: alu_instr = 2; // and
        6'b100101: alu_instr = 3; // or
        6'b000000: alu_instr = 4; // sll
        6'b000010: alu_instr = 5; // srl
        6'b101010: alu_instr = 6; // slt
        6'b001000: begin         // jr instruction
            pc_select = 2;
            alu_instr = 0;
        end
        endcase      
    end

    else if (ir[31:29] == 3'b001) begin // immediate arithmetic
        pc_select = 0;
        write_reg = rt;
        input2_select = 1;
        reg_write = 1;
        if(ir[28:26] != 3'b000 && ir[28:26] != 3'b010) begin
            immediate = unsigned_im;
        end 

        case(ir[28:26])
            3'b000: alu_instr = 0; // addi
            3'b001: alu_instr = 0; // addiu
            3'b010: alu_instr = 6; // slti
            3'b011: alu_instr = 6; // sltiu
            3'b100: alu_instr = 2; // andi
            3'b101: alu_instr = 3; // ori
        endcase        
    end

    else if (ir[31:29] == 3'b011) begin  // branch
        pc_select = 1;
        input2_select = 0;
        reg_write = 0;
        case(ir[28:26])
        3'b000: alu_instr = 7;  // beq
        3'b001: alu_instr = 8;  // bne
        3'b010: alu_instr = 9;  // bgt
        3'b011: alu_instr = 10; // bgte
        3'b100: alu_instr = 11; // ble
        3'b110: alu_instr = 12; // bleq
        endcase
    end

    else if (ir[31:26] == 6'b100011) begin  // lw
        pc_select = 0;
        write_reg = rt;
        input2_select = 1;
        alu_instr = 0;
        lw = 1;
        reg_write = 1;  
    end

    else if (ir[31:26] == 6'b101011) begin  // sw
        pc_select = 0;
        write_reg = rt;
        input2_select = 1;
        alu_instr = 0;
        sw = 1;
        reg_write = 0;     
    end

    else if (ir[31:26] == 2) begin  // j
        pc_select = 3;  
        reg_write = 0;
    end

    else if (ir[31:26]==3) begin  // jal
        pc_select = 3;
        reg_write = 0;
        link = 1;
    end
end
endmodule

memory.v
`timescale 1ns/1ps

module Instruction (rst , clk , addr , instruction);
input wire rst, clk;
input wire[31:0] addr;
output wire[31:0] instruction;
reg[31:0] mem [65535:0];

initial begin
   mem[0] = 32'b00000000100000001000000000100000;   // add $s0, $a0, $0
   mem[1] = 32'b00000000101000001000100000100000;   // add $s1, $a1, $0
   mem[2] = 32'b00100010001100101111111111111111;   // addi $s2, $s1, -1
   mem[3] = 32'b01100010010000000000000000001101;   // Loop1: beq $s2, $0, exit1
   mem[4] = 32'b00000000000000001001100000100000;   // add $s3, $0, $0 
   mem[5] = 32'b01100010011100100000000000001001;   // Loop2: beq $s3, $s2, exit2
   mem[6] = 32'b00000010000100110100000000100000;   // add $t0, $s0, $s3
   mem[7] = 32'b10001101000101000000000000000000;   // lw $s4, 0($t0)
   mem[8] = 32'b10001101000101010000000000000001;   // lw $s5, 1($t0)
   mem[9] = 32'b01111010100101010000000000000011;   // ble $s4, $s5, afterswap
   mem[10] = 32'b10101101000101000000000000000001;  // sw $s4, 1($t0)
   mem[11] = 32'b10101101000101010000000000000000;  // sw $s5, 0($t0)
   mem[12] = 32'b00100010011100110000000000000001;  // addi $s3, $s3, 1
   mem[13] = 32'b00001000000000000000000000000101;  // j Loop2
   mem[14] = 32'b00100010010100101111111111111111;  // addi $s2, $s2, -1
   mem[15] = 32'b00001000000000000000000000000011;  // j Loop1
   mem[16] = 32'b01100000000000000000000000000000;  // exit1: beq $0, $0, 0
end

assign instruction = mem[addr[15:0]];
endmodule


module Data (rst, clk, addr, w_en, data_out, data_in);
input wire rst, clk, w_en;
input wire[31:0] addr, data_in;
output wire[31:0] data_out;
reg[31:0] mem[65535:0];
assign data_out = mem[addr[15:0]];

initial begin
   mem[0] = 15;
   mem[1] = 43;
   mem[2] = 22;
   mem[3] = 8;
   mem[4] = 62;
end

initial begin
   $monitor("%d %d %d %d %d",mem[0],mem[1],mem[2],mem[3],mem[4]);
end

always@(posedge clk) begin
   if (w_en) begin
        mem[addr[15:0]] = data_in;
   end
end
endmodule

alu.v
`timescale 1ns/1ps

module ALU (input1 , input2 , sh_amt, alu_instr , out , branch);
input wire [31:0] input1,input2;
input wire[4:0] sh_amt;
input wire[3:0] alu_instr;
output reg[31:0] out;
output wire branch;
assign branch = (out != 0);

always @(*) begin
    case(alu_instr)
    0: out = input1 + input2;           // add
    1: out = input1 - input2;           // sub
    2: out = input1 & input2;           // and
    3: out = input1 | input2;           // or
    4: out = input1 << sh_amt;          // sll
    5: out = input1 >> sh_amt;          // srl
    6: out = (input1 < input2)?1:0;     // slt
    7: out = (input1 == input2)?1:0;    // beq
    8: out = (input1 != input2)?1:0;    // bne
    9: out = (input1 > input2)?1:0;     // bgt
    10: out = (input1 >= input2)?1:0;   // bgte
    11: out = (input1 < input2)?1:0;    // ble
    12: out = (input1 <= input2)?1:0;   // bleq
    endcase
end
endmodule

mux.v
`timescale 1ns/1ps

module Mux2 (a, b, s, out);
input wire[31:0] a, b;
output wire[31:0] out;
input s;
assign out = a&(~{32{s}}) | b&{32{s}};
endmodule

module Mux4 (a, b, c, d, s, zero, out);
input wire[31:0] a, b, c, d;
input wire[1:0] s;
input wire zero;
output reg[31:0] out;

always @(*) begin
    case(s)
    2'b00: out <= a;
    2'b01: begin
        if (zero)
            out <= b;
        else
            out <= a;
    end
    2'b10: out <= c;
    2'b11: out <= d;
    endcase
end
endmodule

top.v
`timescale 1ns/1ps
`include "memory.v"
`include "control.v"
`include "alu.v"
`include "mux.v"

module top (rst , clk);
input wire rst, clk;

reg [31:0] pc;
wire [31:0] pc_next, ir;
reg[31:0] reg_file[31:0];
wire[31:0] input1, input2;
wire[31:0] rt_data;
reg start;
wire[31:0] data_read; // data read from memory
wire[31:0] alu_out;   // output from ALU
wire[31:0] result;    // final result
wire branch;          // if branch statement evaluates to true
wire [4:0] sh_amt;

wire[1:0] pc_select; // 0 = next line, 1 = branch, 2 = jr, 3 = j
wire[3:0] alu_instr; // which operation alu will preform
wire[4:0] write_reg; // register to write
wire input2_select;  // 0 if input2 is in rt, 1 if immediate
wire sw;             // 1 for sw
wire lw;             // 1 for lw
wire reg_write;      // 1 for writing to register
wire link;           // 1 for jal
wire[31:0] immediate;

wire[31:0] pc_plus1, branch_addr, jr_addr, j_addr;
assign pc_plus1 = pc+1;
assign branch_addr = pc + immediate;
assign jr_addr = input1;
assign j_addr = {pc[31:26] , ir[25:0]};

assign input1 = reg_file[ir[25:21]];
assign rt_data = reg_file[ir[20:16]];
assign sh_amt = ir[10:6];

Mux4 pc_next_selecter(pc_plus1, branch_addr, jr_addr, j_addr, pc_select, branch, pc_next);
Mux2 result_selecter(alu_out, data_read, lw, result);
Mux2 in2_selecter(rt_data, immediate, input2_select, input2);

ALU alu(input1, input2, sh_amt, alu_instr, alu_out, branch);
Instruction instruction(rst, clk, pc, ir);
Data data (rst, clk, alu_out, sw, data_read, rt_data);
control unit (ir, pc_select, alu_instr, write_reg, input2_select, sw, lw, reg_write, link, immediate);

always@(posedge rst) begin
    pc = 0;
    reg_file[4] = 0;   //$a0 = starting index = 0
    reg_file[5] = 5;   //$a1=5=size
    reg_file[0] = 0;   //$zero
    reg_file[29] = 32'd65535;  //$sp
    start = 0;
end

always@(posedge clk) begin
    if(start == 0) start = 1;
    else begin
        if (reg_write) reg_file[write_reg] = result;
        if (link) reg_file[31] = pc_plus1;
        pc = pc_next;
    end
end


endmodule

tb.v
`timescale 1ns/1ps
`include "top.v"

module tb ();
reg clk,rst;

top uut (rst , clk);
initial begin
    clk = 0;
    rst = 1;
    #1 
    rst = 0;
end

initial begin
    $dumpfile("test.vcd");
    $dumpvars(0, tb);
    #2000 
    $finish;
end

always #5 clk=~clk;
endmodule

test.vcd
$date
	Thu Jul 04 16:51:25 2024
$end
$version
	Icarus Verilog
$end
$timescale
	1ps
$end
$scope module tb $end
$var reg 1 ! clk $end
$var reg 1 " rst $end
$scope module uut $end
$var wire 1 ! clk $end
$var wire 32 # input1 [31:0] $end
$var wire 32 $ jr_addr [31:0] $end
$var wire 1 " rst $end
$var wire 32 % rt_data [31:0] $end
$var wire 5 & write_reg [4:0] $end
$var wire 1 ' sw $end
$var wire 5 ( sh_amt [4:0] $end
$var wire 32 ) result [31:0] $end
$var wire 1 * reg_write $end
$var wire 2 + pc_select [1:0] $end
$var wire 32 , pc_plus1 [31:0] $end
$var wire 32 - pc_next [31:0] $end
$var wire 1 . lw $end
$var wire 1 / link $end
$var wire 32 0 j_addr [31:0] $end
$var wire 32 1 ir [31:0] $end
$var wire 1 2 input2_select $end
$var wire 32 3 input2 [31:0] $end
$var wire 32 4 immediate [31:0] $end
$var wire 32 5 data_read [31:0] $end
$var wire 32 6 branch_addr [31:0] $end
$var wire 1 7 branch $end
$var wire 32 8 alu_out [31:0] $end
$var wire 4 9 alu_instr [3:0] $end
$var reg 32 : pc [31:0] $end
$var reg 1 ; start $end
$scope module alu $end
$var wire 32 < input1 [31:0] $end
$var wire 5 = sh_amt [4:0] $end
$var wire 32 > input2 [31:0] $end
$var wire 1 7 branch $end
$var wire 4 ? alu_instr [3:0] $end
$var reg 32 @ out [31:0] $end
$upscope $end
$scope module data $end
$var wire 32 A addr [31:0] $end
$var wire 1 ! clk $end
$var wire 32 B data_in [31:0] $end
$var wire 32 C data_out [31:0] $end
$var wire 1 " rst $end
$var wire 1 ' w_en $end
$upscope $end
$scope module in2_selecter $end
$var wire 32 D a [31:0] $end
$var wire 32 E out [31:0] $end
$var wire 1 2 s $end
$var wire 32 F b [31:0] $end
$upscope $end
$scope module instruction $end
$var wire 32 G addr [31:0] $end
$var wire 1 ! clk $end
$var wire 32 H instruction [31:0] $end
$var wire 1 " rst $end
$upscope $end
$scope module pc_next_selecter $end
$var wire 32 I a [31:0] $end
$var wire 32 J b [31:0] $end
$var wire 32 K c [31:0] $end
$var wire 32 L d [31:0] $end
$var wire 1 7 zero $end
$var wire 2 M s [1:0] $end
$var reg 32 N out [31:0] $end
$upscope $end
$scope module result_selecter $end
$var wire 32 O a [31:0] $end
$var wire 32 P b [31:0] $end
$var wire 32 Q out [31:0] $end
$var wire 1 . s $end
$upscope $end
$scope module unit $end
$var wire 32 R ir [31:0] $end
$var wire 32 S unsigned_im [31:0] $end
$var wire 32 T signed_im [31:0] $end
$var wire 5 U rt [4:0] $end
$var wire 5 V rs [4:0] $end
$var wire 5 W rd [4:0] $end
$var reg 4 X alu_instr [3:0] $end
$var reg 32 Y immediate [31:0] $end
$var reg 1 2 input2_select $end
$var reg 1 / link $end
$var reg 1 . lw $end
$var reg 2 Z pc_select [1:0] $end
$var reg 1 * reg_write $end
$var reg 1 ' sw $end
$var reg 5 [ write_reg [4:0] $end
$upscope $end
$upscope $end
$upscope $end
$enddefinitions $end
$comment Show the parameter values. $end
$dumpall
$end
#0
$dumpvars
b10000 [
b0 Z
b11111111111111111000000000100000 Y
b0 X
b10000 W
b100 V
b0 U
b11111111111111111000000000100000 T
b1000000000100000 S
b100000001000000000100000 R
b0 Q
b1111 P
b0 O
b1 N
b0 M
b100000001000000000100000 L
b0 K
b11111111111111111000000000100000 J
b1 I
b100000001000000000100000 H
b0 G
b11111111111111111000000000100000 F
b0 E
b0 D
b1111 C
b0 B
b0 A
b0 @
b0 ?
b0 >
b0 =
b0 <
0;
b0 :
b0 9
b0 8
07
b11111111111111111000000000100000 6
b1111 5
b11111111111111111000000000100000 4
b0 3
02
b100000001000000000100000 1
b100000001000000000100000 0
0/
0.
b1 -
b1 ,
b0 +
1*
b0 )
b0 (
0'
b10000 &
b0 %
b0 $
b0 #
1"
0!
$end
#1000
0"
#5000
1;
1!
#10000
0!
#15000
b10 -
b10 N
b101 )
b101 Q
bx 5
bx C
bx P
17
b101 8
b101 @
b101 A
b101 O
b10001 &
b10001 [
b11111111111111111000100000100000 4
b11111111111111111000100000100000 F
b11111111111111111000100000100000 Y
b11111111111111111000100000100000 T
b1000100000100000 S
b101 V
b10001 W
b101 $
b101 K
b101 #
b101 <
b101000001000100000100000 0
b101000001000100000100000 L
b101000001000100000100000 1
b101000001000100000100000 H
b101000001000100000100000 R
b10 ,
b10 I
b11111111111111111000100000100001 6
b11111111111111111000100000100001 J
b1 :
b1 G
1!
#20000
0!
#25000
b11 -
b11 N
b100 )
b100 Q
b111110 5
b111110 C
b111110 P
b100 8
b100 @
b100 A
b100 O
b11111111111111111111111111111111 3
b11111111111111111111111111111111 >
b11111111111111111111111111111111 E
12
b10010 &
b10010 [
b11111111111111111111111111111111 4
b11111111111111111111111111111111 F
b11111111111111111111111111111111 Y
b11111111111111111111111111111111 T
b1111111111111111 S
b10001 V
b10010 U
b11111 W
b11111 (
b11111 =
bx %
bx B
bx D
b10001100101111111111111111 0
b10001100101111111111111111 L
b100010001100101111111111111111 1
b100010001100101111111111111111 H
b100010001100101111111111111111 R
b11 ,
b11 I
b1 6
b1 J
b10 :
b10 G
1!
#30000
0!
#35000
b100 -
b100 N
b0 )
b0 Q
b0 3
b0 >
b0 E
b1111 5
b1111 C
b1111 P
07
b0 8
b0 @
b0 A
b0 O
b111 9
b111 ?
b111 X
0*
02
b1 +
b1 M
b1 Z
b1101 4
b1101 F
b1101 Y
b1101 T
b1101 S
b10010 V
b0 U
b0 W
b0 (
b0 =
b100 $
b100 K
b100 #
b100 <
b10010000000000000000001101 0
b10010000000000000000001101 L
b1100010010000000000000000001101 1
b1100010010000000000000000001101 H
b1100010010000000000000000001101 R
b100 ,
b100 I
b10000 6
b10000 J
b11 :
b11 G
b0 %
b0 B
b0 D
1!
#40000
0!
#45000
b101 -
b101 N
b0 9
b0 ?
b0 X
1*
b10011 &
b10011 [
b0 +
b0 M
b0 Z
b11111111111111111001100000100000 4
b11111111111111111001100000100000 F
b11111111111111111001100000100000 Y
b11111111111111111001100000100000 T
b1001100000100000 S
b0 V
b10011 W
b0 $
b0 K
b0 #
b0 <
b1001100000100000 0
b1001100000100000 L
b1001100000100000 1
b1001100000100000 H
b1001100000100000 R
b101 ,
b101 I
b11111111111111111001100000100100 6
b11111111111111111001100000100100 J
b100 :
b100 G
1!
#50000
0!
#55000
b110 -
b110 N
b0 )
b0 Q
b1111 5
b1111 C
b1111 P
b100 3
b100 >
b100 E
07
b0 8
b0 @
b0 A
b0 O
b111 9
b111 ?
b111 X
0*
b1 +
b1 M
b1 Z
b1001 4
b1001 F
b1001 Y
b1001 T
b1001 S
b10011 V
b10010 U
b0 W
b100 %
b100 B
b100 D
b10011100100000000000001001 0
b10011100100000000000001001 L
b1100010011100100000000000001001 1
b1100010011100100000000000001001 H
b1100010011100100000000000001001 R
b110 ,
b110 I
b1110 6
b1110 J
b101 :
b101 G
1!
#60000
0!
#65000
b111 -
b111 N
b0 )
b0 Q
b1111 5
b1111 C
b1111 P
b0 3
b0 >
b0 E
07
b0 8
b0 @
b0 A
b0 O
b0 9
b0 ?
b0 X
1*
b1000 &
b1000 [
b0 +
b0 M
b0 Z
b100000000100000 4
b100000000100000 F
b100000000100000 Y
b100000000100000 T
b100000000100000 S
b10000 V
b10011 U
b1000 W
b0 %
b0 B
b0 D
b10000100110100000000100000 0
b10000100110100000000100000 L
b10000100110100000000100000 1
b10000100110100000000100000 H
b10000100110100000000100000 R
b111 ,
b111 I
b100000000100110 6
b100000000100110 J
b110 :
b110 G
1!
#70000
0!
#75000
b1000 -
b1000 N
b1111 5
b1111 C
b1111 P
07
b0 8
b0 @
b0 A
b0 O
b1111 )
b1111 Q
b0 3
b0 >
b0 E
1.
12
b10100 &
b10100 [
b0 4
b0 F
b0 Y
b0 T
b0 S
b1000 V
b10100 U
b0 W
bx %
bx B
bx D
b1000101000000000000000000 0
b1000101000000000000000000 L
b10001101000101000000000000000000 1
b10001101000101000000000000000000 H
b10001101000101000000000000000000 R
b1000 ,
b1000 I
b111 6
b111 J
b111 :
b111 G
1!
#80000
0!
#85000
b1001 -
b1001 N
b101011 )
b101011 Q
b101011 5
b101011 C
b101011 P
17
b1 8
b1 @
b1 A
b1 O
b1 3
b1 >
b1 E
b10101 &
b10101 [
b1 4
b1 F
b1 Y
1.
b1 T
b1 S
b10101 U
b1000101010000000000000001 0
b1000101010000000000000001 L
b10001101000101010000000000000001 1
b10001101000101010000000000000001 H
b10001101000101010000000000000001 R
b1001 ,
b1001 I
b1001 6
b1001 J
b1000 :
b1000 G
bx %
bx B
bx D
1!
#90000
0!
#95000
b1100 -
b1100 N
b101011 3
b101011 >
b101011 E
b1 )
b1 Q
b101011 5
b101011 C
b101011 P
17
b1 8
b1 @
b1 A
b1 O
b1100 9
b1100 ?
b1100 X
0*
02
b1 +
b1 M
b1 Z
b11 4
b11 F
b11 Y
0.
b11 T
b11 S
b10100 V
b1111 $
b1111 K
b1111 #
b1111 <
b10100101010000000000000011 0
b10100101010000000000000011 L
b1111010100101010000000000000011 1
b1111010100101010000000000000011 H
b1111010100101010000000000000011 R
b1010 ,
b1010 I
b1100 6
b1100 J
b1001 :
b1001 G
b101011 %
b101011 B
b101011 D
1!
#100000
0!
#105000
b1101 -
b1101 N
b1 )
b1 Q
b1 3
b1 >
b1 E
b101011 5
b101011 C
b101011 P
b1 8
b1 @
b1 A
b1 O
b0 9
b0 ?
b0 X
1*
12
b10011 &
b10011 [
b0 +
b0 M
b0 Z
b1 4
b1 F
b1 Y
b1 T
b1 S
b10011 V
b10011 U
b0 %
b0 B
b0 D
b0 $
b0 K
b0 #
b0 <
b10011100110000000000000001 0
b10011100110000000000000001 L
b100010011100110000000000000001 1
b100010011100110000000000000001 H
b100010011100110000000000000001 R
b1101 ,
b1101 I
b1101 6
b1101 J
b1100 :
b1100 G
1!
#110000
0!
#115000
b101 -
b101 N
b101 3
b101 >
b101 E
b101 )
b101 Q
0*
b11 +
b11 M
b11 Z
b101 4
b101 F
b101 Y
b101 T
b101 S
b0 V
b0 U
b101 0
b101 L
bx 5
bx C
bx P
b1000000000000000000000000101 1
b1000000000000000000000000101 H
b1000000000000000000000000101 R
b101 8
b101 @
b101 A
b101 O
b1110 ,
b1110 I
b10010 6
b10010 J
b1101 :
b1101 G
b0 $
b0 K
b0 #
b0 <
b0 %
b0 B
b0 D
1!
#120000
0!
#125000
b110 -
b110 N
b0 )
b0 Q
b100 3
b100 >
b100 E
b1111 5
b1111 C
b1111 P
07
b0 8
b0 @
b0 A
b0 O
b111 9
b111 ?
b111 X
02
b1 +
b1 M
b1 Z
b1001 4
b1001 F
b1001 Y
b1001 T
b1001 S
b10011 V
b10010 U
b100 %
b100 B
b100 D
b1 $
b1 K
b1 #
b1 <
b10011100100000000000001001 0
b10011100100000000000001001 L
b1100010011100100000000000001001 1
b1100010011100100000000000001001 H
b1100010011100100000000000001001 R
b110 ,
b110 I
b1110 6
b1110 J
b101 :
b101 G
1!
#130000
0!
#135000
b111 -
b111 N
b1 )
b1 Q
b1 3
b1 >
b1 E
b101011 5
b101011 C
b101011 P
17
b1 8
b1 @
b1 A
b1 O
b0 9
b0 ?
b0 X
1*
b1000 &
b1000 [
b0 +
b0 M
b0 Z
b100000000100000 4
b100000000100000 F
b100000000100000 Y
b100000000100000 T
b100000000100000 S
b10000 V
b10011 U
b1000 W
b1 %
b1 B
b1 D
b0 $
b0 K
b0 #
b0 <
b10000100110100000000100000 0
b10000100110100000000100000 L
b10000100110100000000100000 1
b10000100110100000000100000 H
b10000100110100000000100000 R
b111 ,
b111 I
b100000000100110 6
b100000000100110 J
b110 :
b110 G
1!
#140000
0!
#145000
b1000 -
b1000 N
b101011 )
b101011 Q
b0 3
b0 >
b0 E
b101011 5
b101011 C
b101011 P
b1 8
b1 @
b1 A
b1 O
1.
12
b10100 &
b10100 [
b0 4
b0 F
b0 Y
b0 T
b0 S
b1000 V
b10100 U
b0 W
b1111 %
b1111 B
b1111 D
b1 $
b1 K
b1 #
b1 <
b1000101000000000000000000 0
b1000101000000000000000000 L
b10001101000101000000000000000000 1
b10001101000101000000000000000000 H
b10001101000101000000000000000000 R
b1000 ,
b1000 I
b111 6
b111 J
b111 :
b111 G
1!
#150000
0!
#155000
b1001 -
b1001 N
b10110 )
b10110 Q
b10110 5
b10110 C
b10110 P
b10 8
b10 @
b10 A
b10 O
b1 3
b1 >
b1 E
b10101 &
b10101 [
b1 4
b1 F
b1 Y
1.
b1 T
b1 S
b10101 U
b1000101010000000000000001 0
b1000101010000000000000001 L
b10001101000101010000000000000001 1
b10001101000101010000000000000001 H
b10001101000101010000000000000001 R
b1001 ,
b1001 I
b1001 6
b1001 J
b1000 :
b1000 G
b101011 %
b101011 B
b101011 D
1!
#160000
0!
#165000
b1010 -
b1010 N
b10110 3
b10110 >
b10110 E
b0 )
b0 Q
b1111 5
b1111 C
b1111 P
07
b0 8
b0 @
b0 A
b0 O
b1100 9
b1100 ?
b1100 X
0*
02
b1 +
b1 M
b1 Z
b11 4
b11 F
b11 Y
0.
b11 T
b11 S
b10100 V
b101011 $
b101011 K
b101011 #
b101011 <
b10100101010000000000000011 0
b10100101010000000000000011 L
b1111010100101010000000000000011 1
b1111010100101010000000000000011 H
b1111010100101010000000000000011 R
b1010 ,
b1010 I
b1100 6
b1100 J
b1001 :
b1001 G
b10110 %
b10110 B
b10110 D
1!
#170000
0!
#175000
b1011 -
b1011 N
b10 )
b10 Q
b1 3
b1 >
b1 E
b10110 5
b10110 C
b10110 P
17
b10 8
b10 @
b10 A
b10 O
1'
b0 9
b0 ?
b0 X
12
b10100 &
b10100 [
b0 +
b0 M
b0 Z
b1 4
b1 F
b1 Y
b1 T
b1 S
b1000 V
b10100 U
b101011 %
b101011 B
b101011 D
b1 $
b1 K
b1 #
b1 <
b1000101000000000000000001 0
b1000101000000000000000001 L
b10101101000101000000000000000001 1
b10101101000101000000000000000001 H
b10101101000101000000000000000001 R
b1011 ,
b1011 I
b1011 6
b1011 J
b1010 :
b1010 G
1!
#180000
0!
#185000
b1100 -
b1100 N
b1 )
b1 Q
b1 8
b1 @
b1 A
b1 O
b0 3
b0 >
b0 E
b10101 &
b10101 [
b0 4
b0 F
b0 Y
1'
b0 T
b0 S
b10101 U
b10110 %
b10110 B
b10110 D
b1000101010000000000000000 0
b1000101010000000000000000 L
b10101101000101010000000000000000 1
b10101101000101010000000000000000 H
b10101101000101010000000000000000 R
b101011 5
b101011 C
b101011 P
b1100 ,
b1100 I
b1011 6
b1011 J
b1011 :
b1011 G
1!
#190000
0!
#195000
b1101 -
b1101 N
b10 )
b10 Q
b10 8
b10 @
b10 A
b10 O
b1 3
b1 >
b1 E
1*
b10011 &
b10011 [
b1 4
b1 F
b1 Y
0'
b1 T
b1 S
b10011 V
b10011 U
b1 %
b1 B
b1 D
b10011100110000000000000001 0
b10011100110000000000000001 L
b100010011100110000000000000001 1
b100010011100110000000000000001 H
b100010011100110000000000000001 R
b1101 ,
b1101 I
b1101 6
b1101 J
b1100 :
b1100 G
b101011 5
b101011 C
b101011 P
1!
#200000
0!
#205000
b101 -
b101 N
b101 3
b101 >
b101 E
b101 )
b101 Q
0*
b11 +
b11 M
b11 Z
b101 4
b101 F
b101 Y
b101 T
b101 S
b0 V
b0 U
b101 0
b101 L
bx 5
bx C
bx P
b1000000000000000000000000101 1
b1000000000000000000000000101 H
b1000000000000000000000000101 R
b101 8
b101 @
b101 A
b101 O
b1110 ,
b1110 I
b10010 6
b10010 J
b1101 :
b1101 G
b0 $
b0 K
b0 #
b0 <
b0 %
b0 B
b0 D
1!
#210000
0!
#215000
b110 -
b110 N
b0 )
b0 Q
b100 3
b100 >
b100 E
b1111 5
b1111 C
b1111 P
07
b0 8
b0 @
b0 A
b0 O
b111 9
b111 ?
b111 X
02
b1 +
b1 M
b1 Z
b1001 4
b1001 F
b1001 Y
b1001 T
b1001 S
b10011 V
b10010 U
b100 %
b100 B
b100 D
b10 $
b10 K
b10 #
b10 <
b10011100100000000000001001 0
b10011100100000000000001001 L
b1100010011100100000000000001001 1
b1100010011100100000000000001001 H
b1100010011100100000000000001001 R
b110 ,
b110 I
b1110 6
b1110 J
b101 :
b101 G
1!
#220000
0!
#225000
b111 -
b111 N
b10 )
b10 Q
b10 3
b10 >
b10 E
b101011 5
b101011 C
b101011 P
17
b10 8
b10 @
b10 A
b10 O
b0 9
b0 ?
b0 X
1*
b1000 &
b1000 [
b0 +
b0 M
b0 Z
b100000000100000 4
b100000000100000 F
b100000000100000 Y
b100000000100000 T
b100000000100000 S
b10000 V
b10011 U
b1000 W
b10 %
b10 B
b10 D
b0 $
b0 K
b0 #
b0 <
b10000100110100000000100000 0
b10000100110100000000100000 L
b10000100110100000000100000 1
b10000100110100000000100000 H
b10000100110100000000100000 R
b111 ,
b111 I
b100000000100110 6
b100000000100110 J
b110 :
b110 G
1!
#230000
0!
#235000
b1000 -
b1000 N
b101011 )
b101011 Q
b0 3
b0 >
b0 E
b101011 5
b101011 C
b101011 P
b10 8
b10 @
b10 A
b10 O
1.
12
b10100 &
b10100 [
b0 4
b0 F
b0 Y
b0 T
b0 S
b1000 V
b10100 U
b0 W
b101011 %
b101011 B
b101011 D
b10 $
b10 K
b10 #
b10 <
b1000101000000000000000000 0
b1000101000000000000000000 L
b10001101000101000000000000000000 1
b10001101000101000000000000000000 H
b10001101000101000000000000000000 R
b1000 ,
b1000 I
b111 6
b111 J
b111 :
b111 G
1!
#240000
0!
#245000
b1001 -
b1001 N
b1000 )
b1000 Q
b1000 5
b1000 C
b1000 P
b11 8
b11 @
b11 A
b11 O
b1 3
b1 >
b1 E
b10101 &
b10101 [
b1 4
b1 F
b1 Y
1.
b1 T
b1 S
b10101 U
b10110 %
b10110 B
b10110 D
b1000101010000000000000001 0
b1000101010000000000000001 L
b10001101000101010000000000000001 1
b10001101000101010000000000000001 H
b10001101000101010000000000000001 R
b1001 ,
b1001 I
b1001 6
b1001 J
b1000 :
b1000 G
1!
#250000
0!
#255000
b1010 -
b1010 N
b1000 3
b1000 >
b1000 E
b0 )
b0 Q
b1111 5
b1111 C
b1111 P
07
b0 8
b0 @
b0 A
b0 O
b1100 9
b1100 ?
b1100 X
0*
02
b1 +
b1 M
b1 Z
b11 4
b11 F
b11 Y
0.
b11 T
b11 S
b10100 V
b101011 $
b101011 K
b101011 #
b101011 <
b10100101010000000000000011 0
b10100101010000000000000011 L
b1111010100101010000000000000011 1
b1111010100101010000000000000011 H
b1111010100101010000000000000011 R
b1010 ,
b1010 I
b1100 6
b1100 J
b1001 :
b1001 G
b1000 %
b1000 B
b1000 D
1!
#260000
0!
#265000
b1011 -
b1011 N
b11 )
b11 Q
b1 3
b1 >
b1 E
b1000 5
b1000 C
b1000 P
17
b11 8
b11 @
b11 A
b11 O
1'
b0 9
b0 ?
b0 X
12
b10100 &
b10100 [
b0 +
b0 M
b0 Z
b1 4
b1 F
b1 Y
b1 T
b1 S
b1000 V
b10100 U
b101011 %
b101011 B
b101011 D
b10 $
b10 K
b10 #
b10 <
b1000101000000000000000001 0
b1000101000000000000000001 L
b10101101000101000000000000000001 1
b10101101000101000000000000000001 H
b10101101000101000000000000000001 R
b1011 ,
b1011 I
b1011 6
b1011 J
b1010 :
b1010 G
1!
#270000
0!
#275000
b1100 -
b1100 N
b10 )
b10 Q
b10 8
b10 @
b10 A
b10 O
b0 3
b0 >
b0 E
b10101 &
b10101 [
b0 4
b0 F
b0 Y
1'
b0 T
b0 S
b10101 U
b1000 %
b1000 B
b1000 D
b1000101010000000000000000 0
b1000101010000000000000000 L
b10101101000101010000000000000000 1
b10101101000101010000000000000000 H
b10101101000101010000000000000000 R
b1100 ,
b1100 I
b1011 6
b1011 J
b1011 :
b1011 G
b101011 5
b101011 C
b101011 P
1!
#280000
0!
#285000
b1101 -
b1101 N
b11 )
b11 Q
b11 8
b11 @
b11 A
b11 O
b1 3
b1 >
b1 E
1*
b10011 &
b10011 [
b1 4
b1 F
b1 Y
0'
b1 T
b1 S
b10011 V
b10011 U
b10 %
b10 B
b10 D
b10011100110000000000000001 0
b10011100110000000000000001 L
b100010011100110000000000000001 1
b100010011100110000000000000001 H
b100010011100110000000000000001 R
b101011 5
b101011 C
b101011 P
b1101 ,
b1101 I
b1101 6
b1101 J
b1100 :
b1100 G
1!
#290000
0!
#295000
b101 -
b101 N
b101 3
b101 >
b101 E
b101 )
b101 Q
0*
b11 +
b11 M
b11 Z
b101 4
b101 F
b101 Y
b101 T
b101 S
b0 V
b0 U
b101 0
b101 L
bx 5
bx C
bx P
b1000000000000000000000000101 1
b1000000000000000000000000101 H
b1000000000000000000000000101 R
b101 8
b101 @
b101 A
b101 O
b1110 ,
b1110 I
b10010 6
b10010 J
b1101 :
b1101 G
b0 $
b0 K
b0 #
b0 <
b0 %
b0 B
b0 D
1!
#300000
0!
